adab/__init__.py
adab/main.py
adab-1.0.4.dist-info/LICENSE
adab-1.0.4.dist-info/METADATA
adab-1.0.4.dist-info/WHEEL
adab-1.0.4.dist-info/top_level.txt
adab-1.0.4.dist-info/RECORD
