Metadata-Version: 2.1
Name: adab
Version: 1.0.4
Summary: مكتبة بايثون مبنية على موقع adab.com، موقع الاشعار والمواضيع الادبية
Home-page: https://github.com/Awiteb/adab
Author: Awiteb
Author-email: Awiteb@hotmail.com
License: UNKNOWN
Keywords: adab,adab.com,arabic,poetry,Arabic poetry
Platform: UNKNOWN
Classifier: Programming Language :: Python :: 3.7
Classifier: Programming Language :: Python :: 3.8
Classifier: Programming Language :: Python :: 3.9
Classifier: Programming Language :: Python :: 3.10
Classifier: License :: OSI Approved :: GNU General Public License v3 (GPLv3)
Classifier: Operating System :: OS Independent
Requires-Python: >=3.7
Requires-Dist: beautifulsoup4 (==4.9.3)
Requires-Dist: certifi (==2021.5.30)
Requires-Dist: charset-normalizer (==2.0.3)
Requires-Dist: idna (==3.2)
Requires-Dist: requests (==2.26.0)
Requires-Dist: soupsieve (==2.2.1)
Requires-Dist: urllib3 (==1.26.6)
